sorrt/__init__.py
sorrt-0.0.2.dist-info/LICENSE
sorrt-0.0.2.dist-info/METADATA
sorrt-0.0.2.dist-info/WHEEL
sorrt-0.0.2.dist-info/entry_points.txt
sorrt-0.0.2.dist-info/top_level.txt
sorrt-0.0.2.dist-info/RECORD
