Metadata-Version: 2.1
Name: sorrt
Version: 0.0.2
Summary: Sorrt
Author-email: Valerio Iacobucci <valerio@valerioiacobucci.com>
Project-URL: Homepage, https://github.com/iacobucci/sorrt
Classifier: Programming Language :: Python :: 3
Classifier: License :: OSI Approved :: MIT License
Classifier: Operating System :: OS Independent
Requires-Python: >=3.7
License-File: LICENSE
